PySSHPass/__init__.py
PySSHPass/pysshpass.py
PySSHPass/helpers/__init__.py
PySSHPass/helpers/ttp_helper.py
pysshpass-0.2.2.dist-info/LICENSE
pysshpass-0.2.2.dist-info/METADATA
pysshpass-0.2.2.dist-info/WHEEL
pysshpass-0.2.2.dist-info/entry_points.txt
pysshpass-0.2.2.dist-info/top_level.txt
pysshpass-0.2.2.dist-info/RECORD
