Metadata-Version: 2.1
Name: pysshpass
Version: 0.2.2
Summary: Python-based, Windows compatible SSH automation client designed to offer a vendor agnostic alternative to Netmiko or `sshpass`.
Home-page: https://github.com/scottpeterman/pysshpass
Author: Scott Peterman
Author-email: scottpeterman@gmail.com
License: GPLv3
Classifier: Programming Language :: Python :: 3.9
Classifier: License :: OSI Approved :: GNU General Public License v3 (GPLv3)
Classifier: Operating System :: OS Independent
License-File: LICENSE
Requires-Dist: paramiko (>=3.5.0)
Requires-Dist: click (>=8.1.7)
Requires-Dist: cryptography (>=43.0.1)
Requires-Dist: PyNaCl (>=1.5.0)
Requires-Dist: tabulate (>=0.9.0)
Requires-Dist: ttp (>=0.9.5)
